onetouch/GPT.py
onetouch/__init__.py
onetouch/chat.py
onetouch/config.py
onetouch/normal_model.py
onetouch/one2three.py
onetouch/readeverything.py
onetouch/superprint.py
onetouch-0.1.31.dist-info/LICENSE
onetouch-0.1.31.dist-info/METADATA
onetouch-0.1.31.dist-info/WHEEL
onetouch-0.1.31.dist-info/top_level.txt
onetouch-0.1.31.dist-info/RECORD
