Metadata-Version: 2.1
Name: onetouch
Version: 0.1.31
Summary: A simple and convenient Python automation toolkit based on libraries such as PyTorch, Pandas, Scikit-learn, Matplotlib, NumPy, etc., offering features like one-click data cleaning, model training, model evaluation, automatic hyperparameter tuning, and prediction.
Home-page: https://gitee.com/SunnyB0y/onetouch
Author: 17fine
Author-email: 2756601885@qq.com
Classifier: Programming Language :: Python :: 3
Classifier: License :: OSI Approved :: MIT License
Classifier: Operating System :: OS Independent
Requires-Python: >=3.6
License-File: LICENSE
Requires-Dist: pandas (>=2.2.2)
Requires-Dist: numpy (>=1.26.4)
Requires-Dist: seaborn (>=0.12.2)
Requires-Dist: matplotlib (>=3.7.2)
Requires-Dist: scikit-learn (>=1.3.2)
Requires-Dist: tqdm (>=4.66.1)
Requires-Dist: tiktoken (>=0.4.0)
Requires-Dist: zhipuai
Provides-Extra: dev
Requires-Dist: flake8 ; extra == 'dev'
Provides-Extra: extra
Requires-Dist: torch ; extra == 'extra'
Requires-Dist: sklearn ; extra == 'extra'
